cs_jobs/__init__.py
cs_jobs/job.py
cs_jobs/task_wrapper.py
cs_jobs-2021.10.1.dist-info/METADATA
cs_jobs-2021.10.1.dist-info/WHEEL
cs_jobs-2021.10.1.dist-info/entry_points.txt
cs_jobs-2021.10.1.dist-info/top_level.txt
cs_jobs-2021.10.1.dist-info/RECORD
